data_memory.v
module data_memory (
	input wire clk,
	input wire mem_write,
	input wire [31:0] address,
	input wire [31:0] write_data,
	output wire [31:0] read_data
);

	reg [31:0] memory [0:255];

	assign read_data = memory[address[9:2]];

	always @(posedge clk) begin
		if (mem_write) begin
			memory[address[9:2]] <= write_data;
		end
	end
endmodule

alu.v
module alu (
    input  wire [31:0] a,
    input  wire [31:0] b,
    input  wire [2:0]  op,
    output reg  [31:0] result,
    output wire        zero
);

    localparam ALU_ADD = 3'b000;
    localparam ALU_SUB = 3'b001;
    localparam ALU_AND = 3'b010;
    localparam ALU_OR  = 3'b011;
    localparam ALU_XOR = 3'b100;

    always @(*) begin
        case (op)
            ALU_ADD: result = a + b;
            ALU_SUB: result = a - b;
            ALU_AND: result = a & b;
            ALU_OR:  result = a | b;
            ALU_XOR: result = a ^ b;
            default: result = 32'b0;
        endcase
    end

    assign zero = (result == 32'b0);

endmodule

alu_control.v
module alu_control (
	input wire [6:0] opcode,
	input wire [2:0] funct3,
	input wire [6:0] funct7,
	output reg [2:0] alu_op
);

	always @(*) begin
		// default: ADD
		alu_op = 3'b000;

		case (opcode)
		 // R-type instructions
			7'b0110011: begin // R-type
				case (funct3)
					3'b000: begin
                                                if (funct7 == 7'b0100000)
                                                    alu_op = 3'b001; // SUB
                                                else
                                                    alu_op = 3'b000; // ADD
					end
					3'b111: alu_op = 3'b010; // AND
					3'b110: alu_op = 3'b011; // OR
					3'b100: alu_op = 3'b100; // XOR
					default:
						alu_op = 3'b000;
				endcase
			end

			// ADDI
			7'b0010011: alu_op = 3'b000; // ADDI

			// LW
			7'b0000011: alu_op = 3'b000; // ADD for address calculation

			// SW
			7'b0100011: alu_op = 3'b000; // ADD for address calculation

			default: begin
				alu_op = 3'b000; // default: ADD
			end
		endcase
	end
endmodule

register_file.v
module register_file (
    input  wire        clk,
    input  wire        write_enable,
    input  wire [4:0]  read_addr1,
    input  wire [4:0]  read_addr2,
    input  wire [4:0]  write_addr,
    input  wire [31:0] write_data,

    output wire [31:0] read_data1,
    output wire [31:0] read_data2
);

    reg [31:0] registers [0:31];

    assign read_data1 =
        (read_addr1 == 5'd0) ? 32'd0 : registers[read_addr1];

    assign read_data2 =
        (read_addr2 == 5'd0) ? 32'd0 : registers[read_addr2];

    always @(posedge clk) begin
        if (write_enable && write_addr != 5'd0) begin
            registers[write_addr] <= write_data;
        end
    end

endmodule

instruction_decoder.v
module instruction_decoder (
    input  wire [31:0] instruction,

    output wire [6:0]  opcode,
    output wire [4:0]  rd,
    output wire [4:0]  rs1,
    output wire [4:0]  rs2,
    output wire [2:0]  funct3,
    output wire [6:0]  funct7,

    output wire [31:0] imm_i,
    output wire [31:0] imm_s,
    output wire [31:0] imm_b
);

    assign opcode = instruction[6:0];
    assign rd     = instruction[11:7];
    assign funct3 = instruction[14:12];
    assign rs1    = instruction[19:15];
    assign rs2    = instruction[24:20];
    assign funct7 = instruction[31:25];

    // I type
    assign imm_i =
        {{20{instruction[31]}},
         instruction[31:20]};

    // S type
    assign imm_s =
        {{20{instruction[31]}},
         instruction[31:25],
         instruction[11:7]};

    // B type
    assign imm_b =
        {{19{instruction[31]}},
         instruction[31],
         instruction[7],
         instruction[30:25],
         instruction[11:8],
         1'b0};

endmodule

instruction_memory.v
module instruction_memory (
    input  wire [31:0] address,
    output wire [31:0] instruction
);

    reg [31:0] memory [0:255];

    initial begin

        // 0x00
        // addi x1, x0, 10
        memory[0] = 32'h00a00093;

        // 0x04
        // addi x2, x0, 10
        memory[1] = 32'h00a00113;

        // 0x08
        // beq x1, x2, +8
        //
        // PC=8 から PC=16 に飛ぶ
        memory[2] = 32'h00208463;

        // 0x0c
        // addi x3, x0, 99
        // branch成功ならskip
        memory[3] = 32'h06300193;

        // 0x10
        // addi x3, x0, 42
        memory[4] = 32'h02a00193;

        // nop
        memory[5] = 32'h00000013;
    end

    assign instruction =
        memory[address[9:2]];

endmodule

program_counter.v
module program_counter (
    input  wire        clk,
    input  wire        reset,
    input  wire  [31:0] next_pc,
    output reg  [31:0] pc
);

    always @(posedge clk) begin
        if (reset)
            pc <= 32'd0;
        else
	  pc <= next_pc;
    end

endmodule

simple_cpu.v
module simple_cpu (
    input wire clk,
    input wire reset
);

    wire [31:0] pc;
    wire [31:0] next_pc;
    wire [31:0] instruction;

    wire [6:0] opcode;
    wire [4:0] rd;
    wire [4:0] rs1;
    wire [4:0] rs2;
    wire [2:0] funct3;
    wire [6:0] funct7;

    wire [31:0] imm_i;
    wire [31:0] imm_s;
    wire [31:0] imm_b;

    wire [31:0] read_data1;
    wire [31:0] read_data2;

    wire [31:0] alu_input_b;
    wire [31:0] alu_result;
    wire [2:0] alu_op;

    wire [31:0] memory_read_data;
    wire [31:0] write_back_data;

    wire is_r_type;
    wire is_addi;
    wire is_lw;
    wire is_sw;
    wire is_beq;

    wire write_enable;
    wire mem_write;

    wire registers_equal;
    wire branch_taken;

    wire [31:0] pc_plus_4;
    wire [31:0] branch_target;

    program_counter pc0 (
        .clk(clk),
        .reset(reset),
        .next_pc(next_pc),
        .pc(pc)
    );

    instruction_memory imem (
        .address(pc),
        .instruction(instruction)
    );

    instruction_decoder decoder (
        .instruction(instruction),
        .opcode(opcode),
        .rd(rd),
        .rs1(rs1),
        .rs2(rs2),
        .funct3(funct3),
        .funct7(funct7),
        .imm_i(imm_i),
        .imm_s(imm_s),
        .imm_b(imm_b)
    );

    assign is_r_type =
        opcode == 7'b0110011;

    assign is_addi =
        opcode == 7'b0010011 &&
        funct3 == 3'b000;

    assign is_lw =
        opcode == 7'b0000011 &&
        funct3 == 3'b010;

    assign is_sw =
        opcode == 7'b0100011 &&
        funct3 == 3'b010;

    assign is_beq =
        opcode == 7'b1100011 &&
        funct3 == 3'b000;

    assign write_enable =
        is_r_type ||
        is_addi ||
        is_lw;

    assign mem_write =
        is_sw;

    register_file rf (
        .clk(clk),
        .write_enable(write_enable),
        .read_addr1(rs1),
        .read_addr2(rs2),
        .write_addr(rd),
        .write_data(write_back_data),
        .read_data1(read_data1),
        .read_data2(read_data2)
    );

    assign alu_input_b =
        is_sw   ? imm_s :
        is_addi ? imm_i :
        is_lw   ? imm_i :
                  read_data2;

    alu_control control (
        .opcode(opcode),
        .funct3(funct3),
        .funct7(funct7),
        .alu_op(alu_op)
    );

    alu alu0 (
        .a(read_data1),
        .b(alu_input_b),
        .op(alu_op),
        .result(alu_result)
    );

    data_memory dmem (
        .clk(clk),
        .mem_write(mem_write),
        .address(alu_result),
        .write_data(read_data2),
        .read_data(memory_read_data)
    );

    assign write_back_data =
        is_lw ? memory_read_data : alu_result;

    //
    // Branch logic
    //

    assign registers_equal =
        read_data1 == read_data2;

    assign branch_taken =
        is_beq && registers_equal;

    assign pc_plus_4 =
        pc + 32'd4;

    assign branch_target =
        pc + imm_b;

    assign next_pc =
        branch_taken
            ? branch_target
            : pc_plus_4;

endmodule

simple_cpu_tb.v
`timescale 1ns/1ps

module simple_cpu_tb;

    reg clk;
    reg reset;

    simple_cpu cpu (
        .clk(clk),
        .reset(reset)
    );

    always #5 clk = ~clk;

    initial begin
        $dumpfile("simple_cpu.vcd");
        $dumpvars(0, simple_cpu_tb);

        clk = 0;
        reset = 1;

        #6;
        reset = 0;

        #50;

        $display("x1 = %d",
            cpu.rf.registers[1]);

        $display("x2 = %d",
            cpu.rf.registers[2]);

        $display("x3 = %d",
            cpu.rf.registers[3]);

        $finish;
    end

endmodule

simple_cpu.vcd
$date
	Tue Sep  1 21:50:17 2026
$end
$version
	Icarus Verilog
$end
$timescale
	1ps
$end
$scope module simple_cpu_tb $end
$var reg 1 ! clk $end
$var reg 1 " reset $end
$scope module cpu $end
$var wire 1 # branch_taken $end
$var wire 1 ! clk $end
$var wire 1 $ is_addi $end
$var wire 1 % is_beq $end
$var wire 1 & is_lw $end
$var wire 1 ' is_sw $end
$var wire 1 ( mem_write $end
$var wire 1 " reset $end
$var wire 1 ) write_enable $end
$var wire 32 * write_back_data [31:0] $end
$var wire 5 + rs2 [4:0] $end
$var wire 5 , rs1 [4:0] $end
$var wire 1 - registers_equal $end
$var wire 32 . read_data2 [31:0] $end
$var wire 32 / read_data1 [31:0] $end
$var wire 5 0 rd [4:0] $end
$var wire 32 1 pc_plus_4 [31:0] $end
$var wire 32 2 pc [31:0] $end
$var wire 7 3 opcode [6:0] $end
$var wire 32 4 next_pc [31:0] $end
$var wire 32 5 memory_read_data [31:0] $end
$var wire 1 6 is_r_type $end
$var wire 32 7 instruction [31:0] $end
$var wire 32 8 imm_s [31:0] $end
$var wire 32 9 imm_i [31:0] $end
$var wire 32 : imm_b [31:0] $end
$var wire 7 ; funct7 [6:0] $end
$var wire 3 < funct3 [2:0] $end
$var wire 32 = branch_target [31:0] $end
$var wire 32 > alu_result [31:0] $end
$var wire 3 ? alu_op [2:0] $end
$var wire 32 @ alu_input_b [31:0] $end
$scope module alu0 $end
$var wire 32 A b [31:0] $end
$var wire 1 B zero $end
$var wire 3 C op [2:0] $end
$var wire 32 D a [31:0] $end
$var parameter 3 E ALU_ADD $end
$var parameter 3 F ALU_AND $end
$var parameter 3 G ALU_OR $end
$var parameter 3 H ALU_SUB $end
$var parameter 3 I ALU_XOR $end
$var reg 32 J result [31:0] $end
$upscope $end
$scope module control $end
$var wire 7 K opcode [6:0] $end
$var wire 7 L funct7 [6:0] $end
$var wire 3 M funct3 [2:0] $end
$var reg 3 N alu_op [2:0] $end
$upscope $end
$scope module decoder $end
$var wire 5 O rs2 [4:0] $end
$var wire 5 P rs1 [4:0] $end
$var wire 5 Q rd [4:0] $end
$var wire 7 R opcode [6:0] $end
$var wire 32 S instruction [31:0] $end
$var wire 32 T imm_s [31:0] $end
$var wire 32 U imm_i [31:0] $end
$var wire 32 V imm_b [31:0] $end
$var wire 7 W funct7 [6:0] $end
$var wire 3 X funct3 [2:0] $end
$upscope $end
$scope module dmem $end
$var wire 32 Y address [31:0] $end
$var wire 1 ! clk $end
$var wire 1 ( mem_write $end
$var wire 32 Z read_data [31:0] $end
$var wire 32 [ write_data [31:0] $end
$upscope $end
$scope module imem $end
$var wire 32 \ instruction [31:0] $end
$var wire 32 ] address [31:0] $end
$upscope $end
$scope module pc0 $end
$var wire 1 ! clk $end
$var wire 32 ^ next_pc [31:0] $end
$var wire 1 " reset $end
$var reg 32 _ pc [31:0] $end
$upscope $end
$scope module rf $end
$var wire 1 ! clk $end
$var wire 5 ` read_addr1 [4:0] $end
$var wire 5 a read_addr2 [4:0] $end
$var wire 5 b write_addr [4:0] $end
$var wire 32 c write_data [31:0] $end
$var wire 1 ) write_enable $end
$var wire 32 d read_data2 [31:0] $end
$var wire 32 e read_data1 [31:0] $end
$upscope $end
$upscope $end
$upscope $end
$enddefinitions $end
$comment Show the parameter values. $end
$dumpall
b100 I
b1 H
b11 G
b10 F
b0 E
$end
#0
$dumpvars
bx e
bx d
bx c
bx b
bx a
bx `
bx _
bx ^
bx ]
bx \
bx [
bx Z
bx Y
bx X
bx W
bx0 V
bx U
bx T
bx S
bx R
bx Q
bx P
bx O
bx N
bx M
bx L
bx K
bx J
bx D
bx C
xB
bx A
bx @
bx ?
bx >
bx =
bx <
bx ;
bx0 :
bx 9
bx 8
bx 7
x6
bx 5
bx 4
bx 3
bx 2
bx 1
bx 0
bx /
bx .
x-
bx ,
bx +
bx *
x)
x(
x'
x&
x%
x$
x#
1"
0!
$end
#5000
b1010 *
b1010 c
b100 4
b100 ^
0B
b1010 >
b1010 J
b1010 Y
b100000000000 =
b100000000000 :
b100000000000 V
0#
b1010 @
b1010 A
1)
b1 8
b1 T
b1010 9
b1010 U
b0 /
b0 D
b0 e
0%
0(
0'
0&
1$
b0 ?
b0 C
b0 N
b0 ;
b0 L
b0 W
b1010 +
b1010 O
b1010 a
b0 ,
b0 P
b0 `
b0 <
b0 M
b0 X
b1 0
b1 Q
b1 b
06
b10011 3
b10011 K
b10011 R
b101000000000000010010011 7
b101000000000000010010011 S
b101000000000000010010011 \
b100 1
b0 2
b0 ]
b0 _
1!
#6000
0"
#10000
0!
#15000
b10 :
b10 V
b10 8
b10 T
b10 0
b10 Q
b10 b
b101000000000000100010011 7
b101000000000000100010011 S
b101000000000000100010011 \
b1000 4
b1000 ^
b110 =
b1000 1
b100 2
b100 ]
b100 _
1!
#20000
0!
#25000
0B
b10100 *
b10100 c
0)
b1010 @
b1010 A
b1000 :
b1000 V
1-
b1010 .
b1010 [
b1010 d
b10100 >
b10100 J
b10100 Y
1#
b1000 8
b1000 T
b10 9
b10 U
b1010 /
b1010 D
b1010 e
1%
0$
b10 +
b10 O
b10 a
b1 ,
b1 P
b1 `
b1000 0
b1000 Q
b1000 b
b1100011 3
b1100011 K
b1100011 R
b1000001000010001100011 7
b1000001000010001100011 S
b1000001000010001100011 \
b10000 4
b10000 ^
b10000 =
b1100 1
b1000 2
b1000 ]
b1000 _
1!
#30000
0!
#35000
b101010 *
b101010 c
1)
b101010 @
b101010 A
b100000100010 :
b100000100010 V
bx .
bx [
bx d
b101010 >
b101010 J
b101010 Y
0#
b100011 8
b100011 T
b101010 9
b101010 U
x-
b0 /
b0 D
b0 e
0%
1$
b1 ;
b1 L
b1 W
b1010 +
b1010 O
b1010 a
b0 ,
b0 P
b0 `
b11 0
b11 Q
b11 b
b10011 3
b10011 K
b10011 R
b10101000000000000110010011 7
b10101000000000000110010011 S
b10101000000000000110010011 \
b10100 4
b10100 ^
b100000110010 =
b10100 1
b10000 2
b10000 ]
b10000 _
1!
#40000
0!
#45000
b0 *
b0 c
1B
b0 >
b0 J
b0 Y
b0 @
b0 A
b0 :
b0 V
b0 8
b0 T
b0 9
b0 U
1-
b0 .
b0 [
b0 d
b0 ;
b0 L
b0 W
b0 +
b0 O
b0 a
b0 0
b0 Q
b0 b
b10011 7
b10011 S
b10011 \
b11000 4
b11000 ^
b10100 =
b11000 1
b10100 2
b10100 ]
b10100 _
1!
#50000
0!
#55000
bx0 :
bx0 V
xB
bx >
bx J
bx Y
x#
bx @
bx A
x)
bx *
bx c
bx 8
bx T
bx 9
bx U
bx .
bx [
bx d
x-
bx /
bx D
bx e
x%
x(
x'
x&
x$
bx ;
bx L
bx W
bx +
bx O
bx a
bx ,
bx P
bx `
bx <
bx M
bx X
bx 0
bx Q
bx b
x6
bx 3
bx K
bx R
bx 7
bx S
bx \
bx 4
bx ^
bx =
b11100 1
b11000 2
b11000 ]
b11000 _
1!
